README.md
setup.py
crosscore/__init__.py
crosscore/_version.py
crosscore/cluster.py
crosscore/commands.py
crosscore/config.py
crosscore/daemon.py
crosscore/terraform.py
crosscore.egg-info/PKG-INFO
crosscore.egg-info/SOURCES.txt
crosscore.egg-info/dependency_links.txt
crosscore.egg-info/requires.txt
crosscore.egg-info/top_level.txt
crosscore/aws/__init__.py
crosscore/aws/templates.py
crosscore/gcp/__init__.py
crosscore/gcp/templates.py
scripts/xcore
scripts/xcore-init
test/test_cluster.py
test/test_daemon.py
test/test_terraform.py