Metadata-Version: 2.1
Name: crosscore
Version: 0.0.1
Summary: A simple cloud-based workflow system
Home-page: https://bitbucket.org/claughton/crosscore
Author: Charlie Laughton
Author-email: charles.laughton@nottingham.ac.uk
License: UNKNOWN
Platform: UNKNOWN
Classifier: Programming Language :: Python :: 3
Classifier: License :: OSI Approved :: BSD License
Classifier: Development Status :: 3 - Alpha
